{"id": "recettes.net", "name": "Recettes.net", "category": "misc", "website_url": "http://www.recettes.net/", "ghostery_id": null, "company_id": "recettes.net", "company_name": "Recettes.net", "iab_vendor": null, "truste_type": null, "description": null, "truste_privacy_url": null, "privacy_url": "", "date_range": ["2019-01", "2019-04"], "domains": ["recettes.net"], "overview": {"reach": 7.569185739740507e-05, "site_reach_top10k": 10, "site_avg_frequency": 0.015062312657551213, "cookies": 0.834797793608116, "bad_qs": 0.0008130757361569236, "tracked": 0.834797793608116, "https": 0.9989004998567877, "requests": 1.825715368055363, "requests_tracking": 1.3012815182341473, "content_length": 522.9485175227061, "requests_failed": 0.46213192153819144, "has_blocking": 0.0015891934843067143, "script": 0.9993809537008805, "iframe": 0.0, "beacon": 0.0, "image": 0.0024577062024743372, "stylesheet": 0.00022174792804279734, "font": 0.000166310946032098, "xhr": 0.0008407942271622733, "plugin": 0.0, "media": 0.0, "referer_leaked": 0.8780478790734633, "referer_leaked_header": 0.6567896443717604, "referer_leaked_url": 0.0, "hosts": 1.0, "reach_rank": 1029, "site_reach_rank": 932}, "reach_time_series": {"page": [8.856803672226871e-05, 8.581335295984875e-05, 8.489805668063193e-05, 7.569185739740507e-05], "ts": ["2019-01", "2019-02", "2019-03", "2019-04"], "site": [12, 5, 8, 10]}, "presence_by_category": [["Reference", 100.0]]}